gempa_terkini/__init__.py
IndonesiaEarthquake_sReport-0.0.4.dist-info/LICENSE
IndonesiaEarthquake_sReport-0.0.4.dist-info/METADATA
IndonesiaEarthquake_sReport-0.0.4.dist-info/WHEEL
IndonesiaEarthquake_sReport-0.0.4.dist-info/top_level.txt
IndonesiaEarthquake_sReport-0.0.4.dist-info/RECORD
