Metadata-Version: 2.1
Name: IndonesiaEarthquake-sReport
Version: 0.0.4
Summary: This is a live earthquake report from Indonesian Agency for Meteorology, Climatology, and Geophysics' s data
Home-page: https://github.com/Muhammad-Sahal-Nurdin/SHL-Indonesia-Earthquake-s-Report
Author: Muhammad Sahal Nurdin
Author-email: sahalnurdin@gmail.com
License: UNKNOWN
Project-URL: Website, https://sahaln.github.io/CV/
Platform: UNKNOWN
Classifier: Programming Language :: Python :: 3
Classifier: License :: OSI Approved :: GNU General Public License v3 (GPLv3)
Classifier: Operating System :: OS Independent
Classifier: Development Status :: 4 - Beta
Requires-Python: >=3.6
License-File: LICENSE
